openbtk/__init__.py
openbtk/models.py
openbtk/encoders/__init__.py
openbtk/encoders/multimodal_encoder.py
openbtk/encoders/text_encoder.py
openbtk-0.1.0.dist-info/METADATA
openbtk-0.1.0.dist-info/WHEEL
openbtk-0.1.0.dist-info/top_level.txt
openbtk-0.1.0.dist-info/RECORD
