Metadata-Version: 2.4
Name: openbtk
Version: 0.1.0
Summary: A multi-modal biomedical vector database ingestion and processing library.
Author: OpenBTK Team
Classifier: Programming Language :: Python :: 3
Classifier: License :: OSI Approved :: MIT License
Classifier: Operating System :: OS Independent
Requires-Python: >=3.8
Requires-Dist: torch
Requires-Dist: transformers
Requires-Dist: pydantic
Requires-Dist: pillow
Requires-Dist: numpy
Requires-Dist: librosa
Dynamic: author
Dynamic: classifier
Dynamic: requires-dist
Dynamic: requires-python
Dynamic: summary
